de2en/__init__.py
de2en/__main__.py
de2en/d2e.pkl
de2en/de2en.py
de2en-0.1.1.dist-info/entry_points.txt
de2en-0.1.1.dist-info/LICENSE
de2en-0.1.1.dist-info/WHEEL
de2en-0.1.1.dist-info/METADATA
de2en-0.1.1.dist-info/RECORD
