Metadata-Version: 2.1
Name: de2en
Version: 0.1.1
Summary: pack_name descr 
Home-page: https://github.com/ffreemt/de2en
License: MIT
Author: ffreemt
Requires-Python: >=3.8.3,<4.0.0
Classifier: License :: OSI Approved :: MIT License
Classifier: Programming Language :: Python :: 3
Classifier: Programming Language :: Python :: 3.10
Classifier: Programming Language :: Python :: 3.9
Requires-Dist: dzbee (>=0.1.1-alpha.2,<0.2.0)
Requires-Dist: ezbee (>=0.1.1,<0.2.0)
Requires-Dist: icecream (>=2.1.1,<3.0.0)
Requires-Dist: install (>=1.3.5,<2.0.0)
Requires-Dist: logzero (>=1.7.0,<2.0.0)
Requires-Dist: word2word (>=1.0.0,<2.0.0)
Project-URL: Repository, https://github.com/ffreemt/de2en
